LICENSE
README.md
setup.py
tromeda/__init__.py
tromeda/get_tropos_datafiles.py
tromeda/tromeda_example.py
tromeda/tromeda_functions.py
tromeda.egg-info/PKG-INFO
tromeda.egg-info/SOURCES.txt
tromeda.egg-info/dependency_links.txt
tromeda.egg-info/requires.txt
tromeda.egg-info/top_level.txt