Metadata-Version: 1.1
Name: tromeda
Version: 0.1.9
Summary: A tool for getting available data-files of TROPOS devices
Home-page: https://github.com/ulysses78/tromeda
Author: Andi Klamt
Author-email: klamt@tropos.de
License: MIT License
Platform: UNKNOWN
Classifier: Development Status :: 1 - Planning
Classifier: Intended Audience :: Science/Research
Classifier: License :: OSI Approved :: BSD License
Classifier: Operating System :: POSIX :: Linux
Classifier: Programming Language :: Python :: 3
Classifier: Programming Language :: Python :: 3.8
